CSolver/__init__.py
CSolver/exceptions.py
CSolver/solver.py
CSolver.py-0.0.8.dist-info/LICENSE
CSolver.py-0.0.8.dist-info/METADATA
CSolver.py-0.0.8.dist-info/WHEEL
CSolver.py-0.0.8.dist-info/top_level.txt
CSolver.py-0.0.8.dist-info/RECORD
